resilient_circuit/__init__.py
resilient_circuit/backoff.py
resilient_circuit/buffer.py
resilient_circuit/circuit_breaker.py
resilient_circuit/cli.py
resilient_circuit/exceptions.py
resilient_circuit/failsafe.py
resilient_circuit/policy.py
resilient_circuit/py.typed
resilient_circuit/retry.py
resilient_circuit/storage.py
resilient_circuit-0.4.7.dist-info/licenses/LICENSE
resilient_circuit-0.4.7.dist-info/METADATA
resilient_circuit-0.4.7.dist-info/WHEEL
resilient_circuit-0.4.7.dist-info/entry_points.txt
resilient_circuit-0.4.7.dist-info/top_level.txt
resilient_circuit-0.4.7.dist-info/RECORD
