Metadata-Version: 2.4
Name: resilient-circuit
Version: 0.4.7
Summary: A resilient circuit breaker and retry library with PostgreSQL support for distributed systems
Author-email: Farshid Ashouri <farsheed.ashouri@gmail.com>
License-Expression: Apache-2.0
Project-URL: Homepage, https://github.com/rodmena-limited/resilient-circuit
Project-URL: Repository, https://github.com/rodmena-limited/resilient-circuit
Project-URL: Documentation, https://resilient-circuit.readthedocs.io
Classifier: Development Status :: 4 - Beta
Classifier: Intended Audience :: Developers
Classifier: Programming Language :: Python :: 3
Classifier: Programming Language :: Python :: 3.9
Classifier: Programming Language :: Python :: 3.10
Classifier: Programming Language :: Python :: 3.11
Classifier: Programming Language :: Python :: 3.12
Classifier: Programming Language :: Python :: 3.13
Classifier: Programming Language :: Python :: 3.14
Classifier: Topic :: Software Development :: Libraries :: Python Modules
Classifier: Topic :: System :: Distributed Computing
Requires-Python: >=3.9
License-File: LICENSE
Requires-Dist: typing-extensions>=4.0.0
Provides-Extra: dev
Requires-Dist: black>=23.0.0; extra == "dev"
Requires-Dist: isort>=5.0.0; extra == "dev"
Requires-Dist: mypy>=1.0.0; extra == "dev"
Requires-Dist: pytest>=7.0.0; extra == "dev"
Requires-Dist: pytest-mock>=3.0.0; extra == "dev"
Requires-Dist: ruff>=0.1.0; extra == "dev"
Provides-Extra: postgres
Requires-Dist: psycopg>=3.1.0; extra == "postgres"
Requires-Dist: python-dotenv>=1.0.0; extra == "postgres"
Provides-Extra: docs
Requires-Dist: sphinx>=7.0.0; extra == "docs"
Requires-Dist: sphinx-rtd-theme>=2.0.0; extra == "docs"
Requires-Dist: sphinx-autodoc-typehints>=1.25.0; extra == "docs"
Dynamic: license-file
